{
  "formatVersion": 1,
  "database": {
    "version": 1,
    "identityHash": "bd775ccb7f701010b8c135c642aa3e6c",
    "entities": [
      {
        "tableName": "students",
        "createSql": "CREATE TABLE IF NOT EXISTS `${TABLE_NAME}` (`id` INTEGER PRIMARY KEY AUTOINCREMENT NOT NULL, `groupName` TEXT NOT NULL, `course` INTEGER NOT NULL, `numberSpecial` INTEGER NOT NULL, `fullName` TEXT NOT NULL, `photo` TEXT, `isBuget` INTEGER NOT NULL, `loginKey` TEXT NOT NULL, `passwordKey` TEXT NOT NULL, `emailKey` TEXT NOT NULL)",
        "fields": [
          {
            "fieldPath": "id",
            "columnName": "id",
            "affinity": "INTEGER",
            "notNull": true
          },
          {
            "fieldPath": "groupName",
            "columnName": "groupName",
            "affinity": "TEXT",
            "notNull": true
          },
          {
            "fieldPath": "course",
            "columnName": "course",
            "affinity": "INTEGER",
            "notNull": true
          },
          {
            "fieldPath": "numberSpecial",
            "columnName": "numberSpecial",
            "affinity": "INTEGER",
            "notNull": true
          },
          {
            "fieldPath": "fullName",
            "columnName": "fullName",
            "affinity": "TEXT",
            "notNull": true
          },
          {
            "fieldPath": "photo",
            "columnName": "photo",
            "affinity": "TEXT"
          },
          {
            "fieldPath": "isBuget",
            "columnName": "isBuget",
            "affinity": "INTEGER",
            "notNull": true
          },
          {
            "fieldPath": "loginKey",
            "columnName": "loginKey",
            "affinity": "TEXT",
            "notNull": true
          },
          {
            "fieldPath": "passwordKey",
            "columnName": "passwordKey",
            "affinity": "TEXT",
            "notNull": true
          },
          {
            "fieldPath": "emailKey",
            "columnName": "emailKey",
            "affinity": "TEXT",
            "notNull": true
          }
        ],
        "primaryKey": {
          "autoGenerate": true,
          "columnNames": [
            "id"
          ]
        }
      },
      {
        "tableName": "teachers",
        "createSql": "CREATE TABLE IF NOT EXISTS `${TABLE_NAME}` (`id` INTEGER PRIMARY KEY AUTOINCREMENT NOT NULL, `fullName` TEXT NOT NULL, `totalHours` INTEGER NOT NULL, `specializationCodes` TEXT NOT NULL, `loginKey` TEXT NOT NULL, `passwordKey` TEXT NOT NULL, `emailKey` TEXT NOT NULL)",
        "fields": [
          {
            "fieldPath": "id",
            "columnName": "id",
            "affinity": "INTEGER",
            "notNull": true
          },
          {
            "fieldPath": "fullName",
            "columnName": "fullName",
            "affinity": "TEXT",
            "notNull": true
          },
          {
            "fieldPath": "totalHours",
            "columnName": "totalHours",
            "affinity": "INTEGER",
            "notNull": true
          },
          {
            "fieldPath": "specializationCodes",
            "columnName": "specializationCodes",
            "affinity": "TEXT",
            "notNull": true
          },
          {
            "fieldPath": "loginKey",
            "columnName": "loginKey",
            "affinity": "TEXT",
            "notNull": true
          },
          {
            "fieldPath": "passwordKey",
            "columnName": "passwordKey",
            "affinity": "TEXT",
            "notNull": true
          },
          {
            "fieldPath": "emailKey",
            "columnName": "emailKey",
            "affinity": "TEXT",
            "notNull": true
          }
        ],
        "primaryKey": {
          "autoGenerate": true,
          "columnNames": [
            "id"
          ]
        }
      }
    ],
    "setupQueries": [
      "CREATE TABLE IF NOT EXISTS room_master_table (id INTEGER PRIMARY KEY,identity_hash TEXT)",
      "INSERT OR REPLACE INTO room_master_table (id,identity_hash) VALUES(42, 'bd775ccb7f701010b8c135c642aa3e6c')"
    ]
  }
}